chaeruldesktop/__init__.py
chaeruldesktop/app_desktop.py
chaeruldesktop/icon/app.ico
chaeruldesktop/icon/circle-user.png
chaeruldesktop/icon/crossed-eye.png
chaeruldesktop/icon/eye.png
chaeruldesktop/icon/lock.png
chaeruldesktop-0.1.7.dist-info/METADATA
chaeruldesktop-0.1.7.dist-info/WHEEL
chaeruldesktop-0.1.7.dist-info/top_level.txt
chaeruldesktop-0.1.7.dist-info/RECORD
