Metadata-Version: 2.4
Name: chaeruldesktop
Version: 0.1.7
Summary: Code ini di buat untuk meringkas kode tkinter menjadi lebih mudah. support terus ya :)
Home-page: https://github.com/chaerul24/chaeruldesktop
Author: Chaerul
Classifier: Programming Language :: Python :: 3
Classifier: Operating System :: OS Independent
Classifier: License :: OSI Approved :: MIT License
Requires-Python: >=3.7
Requires-Dist: customtkinter
Requires-Dist: pillow
Dynamic: author
Dynamic: classifier
Dynamic: description
Dynamic: description-content-type
Dynamic: home-page
Dynamic: requires-dist
Dynamic: requires-python
Dynamic: summary
